<?xml version='1.0' encoding='UTF-8'?>
<ParameterLists><ParameterList name="right1.jpg"><ParameterList name="ROW_0"><Parameter name="X" type="string" value="{1232.2876535599567, 1070.377589014544, 909.9571891477658, 750.98252780188, 594.7181145183159, 441.20956807830316}" /><Parameter name="Y" type="string" value="{460.96875381378516, 465.8973621707723, 471.7626771968278, 478.21111993319994, 485.1827997024408, 492.93656707577685}" /></ParameterList><ParameterList name="ROW_1"><Parameter name="X" type="string" value="{1235.222876414003, 1072.364494776887, 911.3649253472881, 751.7328989752147, 594.7021006239053, 440.7716952665855}" /><Parameter name="Y" type="string" value="{620.5925922784788, 625.1873939474366, 630.2175745197181, 635.8264482043929, 641.8441264411197, 648.5486418818715}" /></ParameterList><ParameterList name="ROW_2"><Parameter name="X" type="string" value="{1237.384294199972, 1074.060293023628, 911.9024579574428, 752.0860794582677, 595.1349254734672, 440.43382076402395}" /><Parameter name="Y" type="string" value="{783.5375930486165, 787.25615090797, 791.4613698335319, 796.216980177885, 801.3656487306739, 806.6103715707186}" /></ParameterList><ParameterList name="ROW_3"><Parameter name="X" type="string" value="{1239.7380574409185, 1076.0297355012112, 913.8227703275609, 753.4857953317473, 596.0754540526356, 440.79788393167104}" /><Parameter name="Y" type="string" value="{946.8652321383437, 950.2187773265656, 953.7131496461466, 957.1936440216249, 961.3654302290362, 965.1953161454621}" /></ParameterList><ParameterList name="ROW_4"><Parameter name="X" type="string" value="{1240.6035807312096, 1076.7896093008858, 914.9024149107322, 754.1408967695239, 595.9896702151847, 440.6610964243966}" /><Parameter name="Y" type="string" value="{1111.5110205897306, 1114.0225212261257, 1116.6207482256177, 1119.3191201548232, 1121.9403598505894, 1124.9435706076345}" /></ParameterList><ParameterList name="ROW_5"><Parameter name="X" type="string" value="{1242.7253595684988, 1078.9202339915014, 916.8763716109657, 756.0969103981711, 597.8765358794905, 442.24233277777086}" /><Parameter name="Y" type="string" value="{1276.1841629070443, 1278.006588858737, 1279.902729626398, 1281.4585272108702, 1283.2487457559089, 1284.9052818564483}" /></ParameterList><ParameterList name="ROW_6"><Parameter name="X" type="string" value="{1244.598253167107, 1080.9257168729202, 918.3884687832781, 757.9138419851938, 600.3074435852435, 444.7779563923306}" /><Parameter name="Y" type="string" value="{1440.8861080681415, 1442.3371561250021, 1443.2704291525308, 1444.0709948828344, 1444.3828777861127, 1444.9376103538796}" /></ParameterList><ParameterList name="ROW_7"><Parameter name="X" type="string" value="{1246.2579792174497, 1082.8441964066626, 920.681796038625, 760.6138676758708, 603.0735331911502, 447.9942575733493}" /><Parameter name="Y" type="string" value="{1604.705399848242, 1605.2065257926915, 1605.40968660409, 1605.3497248670847, 1604.6760689662372, 1603.8862994028943}" /></ParameterList><ParameterList name="ROW_8"><Parameter name="X" type="string" value="{1246.649867298364, 1083.538983327137, 922.497410423533, 762.6241768643035, 605.145743401065, 450.931518654973}" /><Parameter name="Y" type="string" value="{1768.080188218584, 1768.231557966659, 1767.4091201818017, 1766.2897902785746, 1764.6343471902626, 1762.582558399944}" /></ParameterList><ParameterList name="ROW_9"><Parameter name="X" type="string" value="{1247.8287026308526, 1085.5929097102292, 924.7686697588506, 765.4764129497255, 608.616954706373, 454.95784703294044}" /><Parameter name="Y" type="string" value="{1928.3824446930757, 1927.9090252829608, 1926.4370851717752, 1924.5297300916807, 1921.7173450851965, 1918.3674837839937}" /></ParameterList></ParameterList><ParameterList name="right2.jpg"><ParameterList name="ROW_0"><Parameter name="X" type="string" value="{581.333390942769, 743.598776902624, 907.2031047543883, 1072.382142428223, 1237.548611040669, 1402.6610700735855}" /><Parameter name="Y" type="string" value="{1949.5505298070414, 1966.5255225765038, 1982.763684324668, 1998.3937246872192, 2013.385908854595, 2027.3942051145527}" /></ParameterList><ParameterList name="ROW_1"><Parameter name="X" type="string" value="{592.446192102094, 755.823013377349, 920.3441480450982, 1086.4436400354682, 1252.712443521238, 1418.698855780362}" /><Parameter name="Y" type="string" value="{1789.476138933706, 1805.715563891976, 1821.651292861422, 1837.037775864938, 1851.8544510415245, 1865.7306365263114}" /></ParameterList><ParameterList name="ROW_2"><Parameter name="X" type="string" value="{604.7192160621211, 768.8296918454137, 934.8898387419571, 1101.3186822814293, 1268.0169996863456, 1434.884392415594}" /><Parameter name="Y" type="string" value="{1625.747555556366, 1641.6559836016897, 1657.2364814642947, 1672.2885687137482, 1686.740309813607, 1700.9994962997218}" /></ParameterList><ParameterList name="ROW_3"><Parameter name="X" type="string" value="{616.976907336685, 781.9382549476381, 948.2847238189066, 1115.5799188396, 1283.1235453012941, 1450.6793791283822}" /><Parameter name="Y" type="string" value="{1461.202373505607, 1476.2397090494924, 1491.2384823734874, 1506.2975533563178, 1520.5508405820462, 1535.079765620209}" /></ParameterList><ParameterList name="ROW_4"><Parameter name="X" type="string" value="{631.2177441678008, 796.6070426839899, 962.9888216743179, 1131.079172697684, 1299.403116425238, 1467.1529456460457}" /><Parameter name="Y" type="string" value="{1295.0256770080307, 1309.5770267823273, 1324.1533925953797, 1338.6735663940974, 1353.34440627545, 1367.616110894578}" /></ParameterList><ParameterList name="ROW_5"><Parameter name="X" type="string" value="{644.4828838373063, 810.1599458213002, 977.0086158660204, 1145.4301820550215, 1313.96834154543, 1482.1421243132406}" /><Parameter name="Y" type="string" value="{1128.2869783553404, 1142.1527853574148, 1156.0629157559174, 1170.4948034219522, 1184.7498244383924, 1199.1922736761492}" /></ParameterList><ParameterList name="ROW_6"><Parameter name="X" type="string" value="{658.3601459599117, 824.2576817244334, 991.7128047169114, 1160.0672240774722, 1328.1028406337987, 1496.7355207233627}" /><Parameter name="Y" type="string" value="{961.0809026299561, 973.9622178021302, 987.5854335148338, 1001.4116459906503, 1015.8774830199887, 1030.123882159885}" /></ParameterList><ParameterList name="ROW_7"><Parameter name="X" type="string" value="{672.6641780657271, 838.3538052277587, 1005.8867780090417, 1173.9946492328565, 1342.2773414574722, 1510.6432604127378}" /><Parameter name="Y" type="string" value="{794.3356779725016, 806.8700423827064, 819.9084537222473, 833.2832283846128, 847.4115333750603, 861.8177239065577}" /></ParameterList><ParameterList name="ROW_8"><Parameter name="X" type="string" value="{688.3274735902264, 854.048626306604, 1020.7310301564556, 1188.9593479182886, 1357.4431846640903, 1525.1412522349085}" /><Parameter name="Y" type="string" value="{627.695849432726, 639.1996310173433, 651.886641867838, 665.0750278608099, 678.9406695904714, 693.2882000476611}" /></ParameterList><ParameterList name="ROW_9"><Parameter name="X" type="string" value="{703.1780031115709, 868.3959258227059, 1034.9758518767383, 1202.8077870332156, 1370.8966557061924, 1538.3715880363363}" /><Parameter name="Y" type="string" value="{463.5834236256635, 474.4914178925175, 486.58579730183226, 499.2847502439401, 513.0388941899552, 527.455450683205}" /></ParameterList></ParameterList><ParameterList name="right3.jpg"><ParameterList name="ROW_0"><Parameter name="X" type="string" value="{576.1497700893852, 738.34214172463, 901.8822300818687, 1066.9611373562657, 1232.09382022398, 1397.2808165576882}" /><Parameter name="Y" type="string" value="{1951.3150756023563, 1968.4631448096911, 1984.7987920522376, 2000.5747492571304, 2015.6920930065728, 2029.753325807348}" /></ParameterList><ParameterList name="ROW_1"><Parameter name="X" type="string" value="{587.2844242581923, 750.606868954824, 915.0713511238082, 1081.1262590170927, 1247.3480690011731, 1413.3328573849672}" /><Parameter name="Y" type="string" value="{1791.2642360385064, 1807.6976273520809, 1823.7081056895925, 1839.2329061391697, 1854.1891171736008, 1868.1784950277224}" /></ParameterList><ParameterList name="ROW_2"><Parameter name="X" type="string" value="{599.6491050133131, 763.6931855442899, 929.6286454362677, 1096.1008573832096, 1262.7183343983443, 1429.6217502111674}" /><Parameter name="Y" type="string" value="{1627.638171318414, 1643.6734807674131, 1659.3843503207581, 1674.532058042729, 1689.1032726629157, 1703.5130108295607}" /></ParameterList><ParameterList name="ROW_3"><Parameter name="X" type="string" value="{611.9908525859955, 776.8472966579349, 943.1603646436236, 1110.4148896007089, 1277.870831045936, 1445.428406359386}" /><Parameter name="Y" type="string" value="{1463.1615866414809, 1478.303187996359, 1493.4034613506228, 1508.5849052830843, 1522.9213926040586, 1537.603875715981}" /></ParameterList><ParameterList name="ROW_4"><Parameter name="X" type="string" value="{626.304292787639, 791.5774403238211, 957.9475329208741, 1125.9472297064788, 1294.2771569873394, 1462.0712417164177}" /><Parameter name="Y" type="string" value="{1297.0499376545208, 1311.7008878172214, 1326.352385962477, 1341.0174029909217, 1355.7735742275765, 1370.125246003603}" /></ParameterList><ParameterList name="ROW_5"><Parameter name="X" type="string" value="{639.6467438203975, 805.2147578002821, 972.0155670767027, 1140.3823687756733, 1308.9112698034903, 1477.1060306845127}" /><Parameter name="Y" type="string" value="{1130.3829187563545, 1144.3102308657262, 1158.2848964258785, 1172.823422421133, 1187.178889624816, 1201.7182350225264}" /></ParameterList><ParameterList name="ROW_6"><Parameter name="X" type="string" value="{653.5794678316331, 819.3830254252459, 986.7787825993877, 1155.1240279728067, 1323.1719691836918, 1491.7916417882036}" /><Parameter name="Y" type="string" value="{963.1873536585152, 976.1794601953127, 989.8653051070836, 1003.7565640367545, 1018.309533954042, 1032.6477551025023}" /></ParameterList><ParameterList name="ROW_7"><Parameter name="X" type="string" value="{667.9419533521008, 833.5603431821427, 1001.0432413881439, 1169.1404243063944, 1337.4388890958517, 1505.8047146496326}" /><Parameter name="Y" type="string" value="{796.5027405356408, 809.1093079643397, 822.2055147366896, 835.6324338125969, 849.8644261878809, 864.3038870302094}" /></ParameterList><ParameterList name="ROW_8"><Parameter name="X" type="string" value="{683.7396482067317, 849.3701441214404, 1015.9758820519525, 1184.1791238984028, 1352.7055003831538, 1520.473170670891}" /><Parameter name="Y" type="string" value="{629.8295073842277, 641.4437819837767, 654.1703996178263, 667.4378577671264, 681.3298309664797, 695.7576444225283}" /></ParameterList><ParameterList name="ROW_9"><Parameter name="X" type="string" value="{698.6172601470338, 863.7881425563244, 1030.3381559729078, 1198.151195260938, 1366.2287997639887, 1533.7240099979856}" /><Parameter name="Y" type="string" value="{465.74629093767464, 476.7203723157979, 488.8617508335857, 501.6596537310548, 515.448767738278, 529.8799797360437}" /></ParameterList></ParameterList><ParameterList name="right4.jpg"><ParameterList name="ROW_0"><Parameter name="X" type="string" value="{568.2357892279891, 730.2804691542032, 893.7123199906763, 1058.7476194587682, 1223.8388627137037, 1388.9696700670354}" /><Parameter name="Y" type="string" value="{1954.7349083813808, 1971.8957340640143, 1988.2542631104814, 2004.051068500893, 2019.2146393305472, 2033.3421595193086}" /></ParameterList><ParameterList name="ROW_1"><Parameter name="X" type="string" value="{579.2402556781436, 742.4404053199628, 906.7402735439184, 1072.6876561811239, 1238.9663474009162, 1404.9535679113399}" /><Parameter name="Y" type="string" value="{1794.80065439556, 1811.1997029547279, 1827.2685158289669, 1842.7906386130558, 1857.7616569755507, 1871.7295713361896}" /></ParameterList><ParameterList name="ROW_2"><Parameter name="X" type="string" value="{591.4832933206022, 755.3675424408775, 921.2160874993042, 1087.5865417543516, 1254.1973046705255, 1421.1426772922828}" /><Parameter name="Y" type="string" value="{1631.2329223639704, 1647.2937428192743, 1662.9733075005659, 1678.1361199789292, 1692.7226420289987, 1707.0842726610172}" /></ParameterList><ParameterList name="ROW_3"><Parameter name="X" type="string" value="{603.759380643912, 768.4674996397991, 934.6016940547818, 1101.7972587241313, 1269.2942499493715, 1436.8586152452885}" /><Parameter name="Y" type="string" value="{1466.8926916427565, 1481.986881644796, 1497.0688153259862, 1512.2203923249822, 1526.5424123464338, 1541.1651816861854}" /></ParameterList><ParameterList name="ROW_4"><Parameter name="X" type="string" value="{617.9539069731893, 783.1025770331812, 949.2858960513867, 1117.2529328271723, 1285.552005221199, 1453.370581930632}" /><Parameter name="Y" type="string" value="{1300.9038329724733, 1315.4635507367316, 1330.1011981736715, 1344.7032771458337, 1359.4099151862536, 1373.6984928748548}" /></ParameterList><ParameterList name="ROW_5"><Parameter name="X" type="string" value="{631.1383334158203, 796.6242115581707, 963.3024722293129, 1131.6123972272924, 1300.0977278657379, 1468.3632749354654}" /><Parameter name="Y" type="string" value="{1134.2701387850932, 1148.1551828980075, 1162.0694636940061, 1176.5126201639887, 1190.802971452933, 1205.3072209580034}" /></ParameterList><ParameterList name="ROW_6"><Parameter name="X" type="string" value="{645.0524208583989, 810.71864282489, 977.9976476370198, 1146.298279475514, 1314.3115321180119, 1482.9502233763335}" /><Parameter name="Y" type="string" value="{967.1630569626822, 980.0831638780188, 993.646214605212, 1007.4689653798982, 1021.9429143582547, 1036.190365200528}" /></ParameterList><ParameterList name="ROW_7"><Parameter name="X" type="string" value="{659.3059759888283, 824.82915028254, 992.1876185052661, 1160.273968161952, 1328.5080248522966, 1496.9054047807754}" /><Parameter name="Y" type="string" value="{800.5296334039155, 813.047348803837, 826.031126397513, 839.3645484811409, 853.4469261605508, 867.8122557897476}" /></ParameterList><ParameterList name="ROW_8"><Parameter name="X" type="string" value="{675.0410003511574, 840.5244631435955, 1007.0987388978606, 1175.272110397122, 1343.7372135161013, 1511.5557313973175}" /><Parameter name="Y" type="string" value="{633.9503613200138, 645.3947607310323, 657.9884843272241, 671.1448988152605, 684.9305269986146, 699.1868345961333}" /></ParameterList><ParameterList name="ROW_9"><Parameter name="X" type="string" value="{689.8834026159874, 854.9358870825532, 1021.3554388647591, 1189.144738288671, 1357.237192012702, 1524.8140110396316}" /><Parameter name="Y" type="string" value="{469.90109630388406, 480.7003274701391, 492.72093084044974, 505.3403154305429, 518.992736530054, 533.2785389840244}" /></ParameterList></ParameterList><ParameterList name="right5.jpg"><ParameterList name="ROW_0"><Parameter name="X" type="string" value="{563.6142741481323, 725.549057864857, 888.9090596309279, 1053.930834161257, 1219.0202458480333, 1384.1396550117213}" /><Parameter name="Y" type="string" value="{1957.5514402164147, 1974.5043773428454, 1990.7334670091875, 2006.3849198633059, 2021.350844408155, 2035.3876638199636}" /></ParameterList><ParameterList name="ROW_1"><Parameter name="X" type="string" value="{574.4279881406121, 737.4910760687532, 901.7495897059308, 1067.6311429744258, 1233.8903572874954, 1399.921351120536}" /><Parameter name="Y" type="string" value="{1797.6108758022344, 1813.8896200277181, 1829.7640281312301, 1845.1142478805577, 1859.96827800064, 1873.8060835742842}" /></ParameterList><ParameterList name="ROW_2"><Parameter name="X" type="string" value="{586.4513210694768, 750.1719499051953, 915.9545622742589, 1082.2592195849058, 1248.8868498787458, 1415.8146293409623}" /><Parameter name="Y" type="string" value="{1634.1398158120223, 1650.018853262967, 1665.4980173851243, 1680.5058692934579, 1694.9130565184007, 1709.107761340884}" /></ParameterList><ParameterList name="ROW_3"><Parameter name="X" type="string" value="{598.4505533130039, 763.0451492218327, 929.1229487954605, 1096.2050978153252, 1263.7284370112177, 1431.358524075235}" /><Parameter name="Y" type="string" value="{1469.8489505502525, 1484.786811359798, 1499.6654233494758, 1514.6524174125718, 1528.7665836147842, 1543.1792569913919}" /></ParameterList><ParameterList name="ROW_4"><Parameter name="X" type="string" value="{612.3570994405188, 777.4347363595256, 943.5624135776561, 1111.4735155722383, 1279.7893260555347, 1447.5955791450242}" /><Parameter name="Y" type="string" value="{1303.9171223652772, 1318.330187210094, 1332.7262709397576, 1347.11350000174, 1361.5949986374465, 1375.697514959979}" /></ParameterList><ParameterList name="ROW_5"><Parameter name="X" type="string" value="{625.3545009558225, 790.7140240555676, 957.4999285321074, 1125.6423426249721, 1294.2496729415968, 1462.400407030025}" /><Parameter name="Y" type="string" value="{1137.37266457617, 1151.0479636652094, 1164.7780466038255, 1178.9579116699852, 1193.0379681585596, 1207.2650048610665}" /></ParameterList><ParameterList name="ROW_6"><Parameter name="X" type="string" value="{639.025158979629, 804.5948615001959, 971.8033410783781, 1140.058873417736, 1308.0953043936186, 1476.774244735912}" /><Parameter name="Y" type="string" value="{970.2661945733488, 982.9852172220715, 996.307729724661, 1009.9049662016438, 1024.1376443817578, 1038.130442609108}" /></ParameterList><ParameterList name="ROW_7"><Parameter name="X" type="string" value="{653.0894064647784, 818.4947708068867, 985.801783593795, 1153.8223109902858, 1322.1101934883038, 1490.5674801574664}" /><Parameter name="Y" type="string" value="{803.6896775733882, 815.9449616062861, 828.7104232717885, 841.7968278366923, 855.6444454464192, 869.7601556453875}" /></ParameterList><ParameterList name="ROW_8"><Parameter name="X" type="string" value="{668.6073157038132, 833.9802260667477, 1000.4560983388677, 1168.6092456039432, 1337.1243352653062, 1504.9927942185393}" /><Parameter name="Y" type="string" value="{637.1547386568521, 648.3446968859979, 660.6758920437743, 673.5745947432378, 687.0986818429235, 701.0797367058426}" /></ParameterList><ParameterList name="ROW_9"><Parameter name="X" type="string" value="{683.2335370975546, 848.1884236410702, 1014.5407988475279, 1182.3113904646837, 1350.4510678366046, 1518.053613390815}" /><Parameter name="Y" type="string" value="{473.100038945149, 483.6639657897005, 495.39229355466443, 507.74335761522264, 521.1307790495355, 535.1162870706124}" /></ParameterList></ParameterList></ParameterLists>